Metadata-Version: 1.0
Name: distributions-lex
Version: 0.1
Summary: Gaussian distributions
Home-page: UNKNOWN
Author: Alex Macharia
Author-email: alex.machariam@gmail.com
License: UNKNOWN
Platform: UNKNOWN
